nonebot_plugin_moegoe/__init__.py
nonebot_plugin_moegoe/profile.toml
nonebot_plugin_moegoe/utils.py
nonebot_plugin_moegoe-0.10.6.dist-info/LICENSE
nonebot_plugin_moegoe-0.10.6.dist-info/METADATA
nonebot_plugin_moegoe-0.10.6.dist-info/WHEEL
nonebot_plugin_moegoe-0.10.6.dist-info/RECORD
