Metadata-Version: 2.1
Name: nonebot-plugin-moegoe
Version: 0.10.6
Summary: VITS AI合成原神角色语音
Home-page: https://github.com/yiyuiii/nonebot-plugin-moegoe
License: MIT
Keywords: nonebot,nonebot2,moegoe
Author: yiyuiii
Author-email: yiyuiii@foxmail.com
Requires-Python: >=3.8,<4.0
Classifier: License :: OSI Approved :: MIT License
Classifier: Programming Language :: Python :: 3
Classifier: Programming Language :: Python :: 3.8
Classifier: Programming Language :: Python :: 3.9
Classifier: Programming Language :: Python :: 3.10
Classifier: Programming Language :: Python :: 3.11
Classifier: Programming Language :: Python :: 3.12
Requires-Dist: gradio_client (>=0.7.0,<0.8.0)
Requires-Dist: httpx (>=0.23.0,<0.24.0)
Requires-Dist: nonebot-adapter-onebot (>=2.1.1,<3.0.0)
Requires-Dist: nonebot2 (>=2.0.0b5,<3.0.0)
Requires-Dist: rtoml (>=0.9.0,<0.10.0)
Project-URL: Documentation, https://github.com/yiyuiii/nonebot-plugin-moegoe#readme
Project-URL: Repository, https://github.com/yiyuiii/nonebot-plugin-moegoe
